xeye/__init__.py
xeye/build_dataset.py
xeye/dataset.py
xeye/manual_dataset.py
xeye-1.6.dist-info/LICENSE
xeye-1.6.dist-info/METADATA
xeye-1.6.dist-info/WHEEL
xeye-1.6.dist-info/top_level.txt
xeye-1.6.dist-info/RECORD
