Metadata-Version: 2.1
Name: xeye
Version: 1.6
Summary: Create datasets for computer vision applications
Author-email: Marco Salvalaggio <mar.salvalaggio@gmail.com>
License: Copyright (c) 2018 The Python Packaging Authority
Project-URL: Homepage, https://github.com/marcosalvalaggio/xeye
Project-URL: Bug Tracker, https://github.com/marcosalvalaggio/xeye
Classifier: Programming Language :: Python :: 3
Classifier: License :: OSI Approved :: MIT License
Classifier: Operating System :: OS Independent
Requires-Python: >=3.7
License-File: LICENSE
Requires-Dist: opencv-python
Requires-Dist: numpy
Requires-Dist: scikit-learn
